stylish_onnx/__init__.py
stylish_onnx/py.typed
stylish_onnx-0.1.0.dist-info/METADATA
stylish_onnx-0.1.0.dist-info/WHEEL
stylish_onnx-0.1.0.dist-info/RECORD
